bqskit/ft/__init__.py
bqskit/ft/ftmodel.py
bqskit/ft/cliffordrz/cliffordrzgates.py
bqskit/ft/cliffordrz/cliffordrzmodel.py
bqskit/ft/cliffordrz/defaultworkflow.py
bqskit/ft/cliffordt/cliffordtgates.py
bqskit/ft/cliffordt/cliffordtmodel.py
bqskit/ft/cliffordt/defaultworkflow.py
bqskit/ft/ftpasses/__init__.py
bqskit/ft/ftpasses/gridsynth.py
bqskit/ft/ftpasses/rounding.py
bqskit/ft/rules/isolate_rz.py
bqskit/ft/rules/replacement.py
bqskit_ft-0.2.0.dist-info/licenses/LICENSE
tests/ft/test_compile.py
tests/ft/test_gridsynth.py
tests/ft/test_replacement.py
bqskit_ft-0.2.0.dist-info/METADATA
bqskit_ft-0.2.0.dist-info/WHEEL
bqskit_ft-0.2.0.dist-info/top_level.txt
bqskit_ft-0.2.0.dist-info/RECORD
