Metadata-Version: 2.4
Name: bqskit-ft
Version: 0.2.0
Summary: BQSKit extension for compiling to Fault-Tolerant gate sets.
Author-email: Mathias Weiden <mtweiden@berkeley.edu>
License: BSD-3-Clause
Project-URL: Homepage, https://github.com/BQSKit/bqskit-ft
Project-URL: Repository, https://github.com/BQSKit/bqskit-ft
Project-URL: Issues, https://github.com/BQSKit/bqskit-ft/issues
Project-URL: Documentation, https://github.com/BQSKit/bqskit-ft/blob/main/README.md
Keywords: quantum computing,compilation,fault-tolerant,clifford+t
Classifier: Development Status :: 3 - Alpha
Classifier: Intended Audience :: Developers
Classifier: Intended Audience :: Science/Research
Classifier: Operating System :: OS Independent
Classifier: Programming Language :: Python :: 3
Classifier: Programming Language :: Python :: 3.8
Classifier: Programming Language :: Python :: 3.9
Classifier: Programming Language :: Python :: 3.10
Classifier: Programming Language :: Python :: 3.11
Classifier: Programming Language :: Python :: 3.12
Classifier: Topic :: Scientific/Engineering :: Physics
Classifier: Topic :: Software Development :: Libraries :: Python Modules
Requires-Python: >=3.8
License-File: LICENSE
Requires-Dist: bqskit
Requires-Dist: numpy
Requires-Dist: scipy
Requires-Dist: pygridsynth
Dynamic: license-file
